{
  "unversionedId": "howtouse/congratulations",
  "id": "howtouse/congratulations",
  "title": "Congratulations!",
  "description": "You have just learned the basics of Docusaurus and made some changes to the initial template.",
  "source": "@site/docs/howtouse/congratulations.md",
  "sourceDirName": "howtouse",
  "slug": "/howtouse/congratulations",
  "permalink": "/AdaCAD/docs/howtouse/congratulations",
  "draft": false,
  "tags": [],
  "version": "current",
  "sidebarPosition": 6,
  "frontMatter": {
    "sidebar_position": 6
  },
  "sidebar": "tutorialSidebar",
  "previous": {
    "title": "Deploy your site",
    "permalink": "/AdaCAD/docs/howtouse/deploy-your-site"
  },
  "next": {
    "title": "How to Develop AdaCAD Operations",
    "permalink": "/AdaCAD/docs/category/how-to-develop-adacad-operations"
  }
}